[
  {
    "anonymous": false,
    "inputs": [
      {
        "indexed": true,
        "internalType": "address",
        "name": "client",
        "type": "address"
      }
    ],
    "name": "AccessGranted",
    "type": "event"
  },
  {
    "inputs": [
      {
        "internalType": "string",
        "name": "_entry",
        "type": "string"
      }
    ],
    "name": "addEntry",
    "outputs": [],
    "stateMutability": "nonpayable",
    "type": "function"
  },
  {
    "inputs": [],
    "name": "deposit",
    "outputs": [],
    "stateMutability": "payable",
    "type": "function"
  },
  {
    "inputs": [],
    "name": "grantAccess",
    "outputs": [],
    "stateMutability": "payable",
    "type": "function"
  },
  {
    "anonymous": false,
    "inputs": [
      {
        "indexed": true,
        "internalType": "address",
        "name": "client",
        "type": "address"
      },
      {
        "indexed": false,
        "internalType": "uint256",
        "name": "amount",
        "type": "uint256"
      }
    ],
    "name": "PaymentReceived",
    "type": "event"
  },
  {
    "inputs": [
      {
        "internalType": "address",
        "name": "_MoneySender",
        "type": "address"
      },
      {
        "internalType": "string",
        "name": "_sharedText",
        "type": "string"
      },
      {
        "internalType": "uint256",
        "name": "_cash",
        "type": "uint256"
      }
    ],
    "name": "shareWith",
    "outputs": [],
    "stateMutability": "payable",
    "type": "function"
  },
  {
    "anonymous": false,
    "inputs": [
      {
        "indexed": true,
        "internalType": "address",
        "name": "user",
        "type": "address"
      },
      {
        "indexed": false,
        "internalType": "string[]",
        "name": "text",
        "type": "string[]"
      }
    ],
    "name": "TextUpdated",
    "type": "event"
  },
  {
    "anonymous": false,
    "inputs": [
      {
        "indexed": true,
        "internalType": "address",
        "name": "client",
        "type": "address"
      }
    ],
    "name": "sharedAccessGranted",
    "type": "event"
  },
  {
    "inputs": [
      {
        "internalType": "uint256",
        "name": "_amount",
        "type": "uint256"
      }
    ],
    "name": "withdrawPayment",
    "outputs": [],
    "stateMutability": "nonpayable",
    "type": "function"
  },
  {
    "inputs": [],
    "name": "getClientBalance",
    "outputs": [
      {
        "internalType": "uint256",
        "name": "",
        "type": "uint256"
      }
    ],
    "stateMutability": "view",
    "type": "function"
  },
  {
    "inputs": [],
    "name": "getEntries",
    "outputs": [
      {
        "internalType": "string[]",
        "name": "",
        "type": "string[]"
      }
    ],
    "stateMutability": "view",
    "type": "function"
  },
  {
    "inputs": [],
    "name": "getSharedEntries",
    "outputs": [
      {
        "internalType": "string[]",
        "name": "",
        "type": "string[]"
      }
    ],
    "stateMutability": "view",
    "type": "function"
  },
  {
    "inputs": [],
    "name": "owner",
    "outputs": [
      {
        "internalType": "address payable",
        "name": "",
        "type": "address"
      }
    ],
    "stateMutability": "view",
    "type": "function"
  }
]